trendmaster/__init__.py
trendmaster/trendmaster.py
trendmaster-0.2.3.dist-info/LICENSE
trendmaster-0.2.3.dist-info/METADATA
trendmaster-0.2.3.dist-info/WHEEL
trendmaster-0.2.3.dist-info/entry_points.txt
trendmaster-0.2.3.dist-info/top_level.txt
trendmaster-0.2.3.dist-info/RECORD
