Metadata-Version: 2.1
Name: trendmaster
Version: 0.2.3
Summary: Stock Price Prediction using Transformer Deep Learning Architecture
Home-page: https://github.com/hemangjoshi37a/TrendMaster
Author: Hemang Joshi
Author-email: hemangjoshi37a@gmail.com
Classifier: Development Status :: 3 - Alpha
Classifier: Intended Audience :: Developers
Classifier: License :: OSI Approved :: MIT License
Classifier: Operating System :: OS Independent
Classifier: Programming Language :: Python :: 3
Classifier: Programming Language :: Python :: 3.7
Classifier: Programming Language :: Python :: 3.8
Classifier: Programming Language :: Python :: 3.9
Requires-Python: >=3.7
License-File: LICENSE
Requires-Dist: numpy
Requires-Dist: pandas
Requires-Dist: torch
Requires-Dist: transformers
Requires-Dist: matplotlib
Requires-Dist: tqdm
Requires-Dist: joblib
Requires-Dist: scikit-learn
Requires-Dist: jugaad-trader
